{
  "id": "airbus-a330-003",
  "familyId": "airbus-a330",
  "familyName": "Airbus A330",
  "source": {
    "provider": "jetphotos",
    "originalLink": "https://www.jetphotos.com/photo/12037598",
    "photoPageUrl": "https://www.jetphotos.com/photo/12037598",
    "imageUrl": "https://cdn.jetphotos.com/full/6/1065250_1772958266.jpg",
    "searchUrl": "https://www.jetphotos.com/showphotos.php?aircraft=Airbus+A330%3B&airline=all&country-location=all&photographer-group=all&keywords-contain=3&keywords=&photo-year=all&width=&height=&genre=&search-type=Advanced&sort-order=0",
    "searchAircraft": "Airbus A330;",
    "photographer": "Biochemical ZBTJ",
    "licenseStatus": "unknown",
    "termsNote": "JetPhotos page says to contact photographer for terms of use.",
    "jetphotosPhotoId": "12037598"
  },
  "aircraft": {
    "exactType": "Airbus A330-941",
    "normalizedFamily": "Airbus A330",
    "registration": "B-58303",
    "serialNumber": null,
    "airline": "Starlux"
  },
  "photo": {
    "photoDate": "Feb 21, 2026",
    "uploadedDate": "Mar 29, 2026",
    "locationName": "Fukuoka Airport - RJFF",
    "locationCountry": null,
    "notes": null
  },
  "files": {
    "sourceJpg": "data/aircraft-sources/airbus-a330/003.jpg",
    "sidecar": "data/aircraft-sources/airbus-a330/003.json",
    "publicWebp": "public/assets/aircraft/airbus-a330/003.webp"
  },
  "image": {
    "width": null,
    "height": null,
    "sha256": "0c75a82f9450a499d34a7bf5592ac16deb3e091de3e76c1250e1130e5558bfcb",
    "sizeBytes": 1010800
  },
  "curation": {
    "approved": false,
    "notes": ""
  },
  "importedAt": "2026-03-29T10:17:52.930Z"
}
