{
  "id": "airbus-a330-067",
  "familyId": "airbus-a330",
  "familyName": "Airbus A330",
  "source": {
    "provider": "jetphotos",
    "originalLink": "https://www.jetphotos.com/photo/12036610",
    "photoPageUrl": "https://www.jetphotos.com/photo/12036610",
    "imageUrl": "https://cdn.jetphotos.com/full/6/693410_1772805091.jpg",
    "searchUrl": "https://www.jetphotos.com/showphotos.php?aircraft=Airbus+A330%3B&airline=all&country-location=all&photographer-group=all&keywords-contain=3&keywords=&photo-year=all&width=&height=&genre=&search-type=Advanced&sort-order=0",
    "searchAircraft": "Airbus A330;",
    "photographer": "Jack Green",
    "licenseStatus": "unknown",
    "termsNote": "JetPhotos page says to contact photographer for terms of use.",
    "jetphotosPhotoId": "12036610"
  },
  "aircraft": {
    "exactType": "Airbus A330-941",
    "normalizedFamily": "Airbus A330",
    "registration": "RP-C3904",
    "serialNumber": null,
    "airline": "Cebu Pacific Air"
  },
  "photo": {
    "photoDate": "Jan 14, 2026",
    "uploadedDate": "Mar 27, 2026",
    "locationName": "Hong Kong-Chek Lap Kok Int'l Airport - VHHH",
    "locationCountry": null,
    "notes": null
  },
  "files": {
    "sourceJpg": "data/aircraft-sources/airbus-a330/067.jpg",
    "sidecar": "data/aircraft-sources/airbus-a330/067.json",
    "publicWebp": "public/assets/aircraft/airbus-a330/067.webp"
  },
  "image": {
    "width": null,
    "height": null,
    "sha256": "efb2ea80e3e670dcab982465ee322c6e4d212742eeac11be61785173049a2b5b",
    "sizeBytes": 720628
  },
  "curation": {
    "approved": false,
    "notes": ""
  },
  "importedAt": "2026-03-29T10:19:13.078Z"
}
